helloworldbasic4message/__init__.py
helloworldbasic4message/mymessage.py
helloworldbasic4message/original__init__.py
helloworldbasic4message/prev__init__.py
helloworldbasic4message/utility.py
helloworldbasic4message/utility1.py
helloworldbasic4message/utility2.py
helloworldbasic4message/_previous_inits/__init__.py
helloworldbasic4message/_previous_inits/prev__init__.py
helloworldbasic4message/_previous_inits/utility1.py
helloworldbasic4message/_previous_inits/utility2.py
helloworldbasic4message/utils/__init__.py
helloworldbasic4message/utils/utility1.py
helloworldbasic4message/utils/utility2.py
remove/__init__.py
helloworldbasic4message-2.0.18.dist-info/METADATA
helloworldbasic4message-2.0.18.dist-info/WHEEL
helloworldbasic4message-2.0.18.dist-info/top_level.txt
helloworldbasic4message-2.0.18.dist-info/RECORD
