Metadata-Version: 2.1
Name: helloworldbasic4message
Version: 2.0.18
Summary: short desc here
Author: Mariano Rico
Author-email: <marstab4@gmail.com>
Keywords: python,hello
Classifier: Development Status :: 1 - Planning
Classifier: Intended Audience :: Developers
Classifier: Programming Language :: Python :: 3
Classifier: Operating System :: Unix
Classifier: Operating System :: MacOS :: MacOS X
Classifier: Operating System :: Microsoft :: Windows
Requires-Dist: fpdf2
Requires-Dist: python-docx
